README.rst
setup.cfg
setup.py
levup/__about__.py
levup/__init__.py
levup/core.py
levup.egg-info/PKG-INFO
levup.egg-info/PKG-INFO.bak
levup.egg-info/SOURCES.txt
levup.egg-info/SOURCES.txt.bak
levup.egg-info/dependency_links.txt
levup.egg-info/requires.txt
levup.egg-info/top_level.txt
levup.egg-info/top_level.txt.bak