Metadata-Version: 2.4
Name: levup
Version: 0.3
Summary: made-iraq Python implementation
Home-page: https://t.me/NasrPy
Author: Nasr
Author-email: nasr2python@gmail.com
Keywords: made-iraq
Requires-Dist: six
Dynamic: author
Dynamic: author-email
Dynamic: home-page
Dynamic: keywords
Dynamic: requires-dist
Dynamic: summary
